ipyrun/__init__.py
ipyrun/_dev_sys_path_append.py
ipyrun/_utils.py
ipyrun/_version.py
ipyrun/actions.py
ipyrun/basemodel.py
ipyrun/constants.py
ipyrun/runshell.py
ipyrun/runui.py
ipyrun/ui_add.py
ipyrun/ui_remove.py
ipyrun/ui_wizard.py
ipyrun/examples/linegraph/linegraph_app.py
ipyrun/examples/linegraph/linegraph/__main__.py
ipyrun/examples/linegraph/linegraph/input_schema_linegraph.py
ipyrun/examples/linegraph/linegraph/make_graph.py
ipyrun-0.6.2.dist-info/METADATA
ipyrun-0.6.2.dist-info/WHEEL
ipyrun-0.6.2.dist-info/RECORD
