Metadata-Version: 2.4
Name: ipyrun
Version: 0.6.2
Summary: template UI (ipywidgets / ipyautoui) for running python scripts in jupyterlab / voila.
Project-URL: Homepage, https://github.com/maxfordham/ipyrun
Author-email: John Gunstone <gunstone.john@gmail.com>
Keywords: ipyrun
Classifier: Development Status :: 2 - Pre-Alpha
Classifier: Intended Audience :: Developers
Classifier: Natural Language :: English
Classifier: Programming Language :: Python :: 3.9
Requires-Dist: emoji
Requires-Dist: halo
Requires-Dist: immutables
Requires-Dist: ipyautoui==0.7.1
Requires-Dist: jinja2
Requires-Dist: pydantic>2
Requires-Dist: pyyaml
Requires-Dist: stringcase
